myfunction_ViktoriyaXIII/__init__.py
myfunction_ViktoriyaXIII/math.py
myfunction_ViktoriyaXIII-0.0.8.dist-info/METADATA
myfunction_ViktoriyaXIII-0.0.8.dist-info/WHEEL
myfunction_ViktoriyaXIII-0.0.8.dist-info/top_level.txt
myfunction_ViktoriyaXIII-0.0.8.dist-info/RECORD
