Metadata-Version: 2.1
Name: myfunction-ViktoriyaXIII
Version: 0.0.8
Summary: A description of your package
Home-page: https://github.com/ViktoriyaXIII
Author: Viktoriia
Author-email: viktoriya.bielova@gmail.com
License: MIT
Platform: UNKNOWN
Classifier: Programming Language :: Python :: 3
Classifier: License :: OSI Approved :: MIT License
Classifier: Operating System :: OS Independent
Requires-Python: >=3.6
Requires-Dist: os
